slurmbatcher/__init__.py
slurmbatcher/__main__.py
slurmbatcher/cli.py
slurmbatcher/logging.py
slurmbatcher/shformat.py
slurmbatcher/types.py
slurmbatcher/utils.py
slurmbatcher-0.3.4.dist-info/LICENSE
slurmbatcher-0.3.4.dist-info/METADATA
slurmbatcher-0.3.4.dist-info/WHEEL
slurmbatcher-0.3.4.dist-info/entry_points.txt
slurmbatcher-0.3.4.dist-info/RECORD
