Metadata-Version: 2.1
Name: slurmbatcher
Version: 0.3.4
Summary: 
Home-page: https://github.com/dangrie158/slurmbatcher
License: MIT
Author: Daniel Grießhaber
Author-email: griesshaber@hdm-stuttgart.de
Requires-Python: >=3.11,<4.0
Classifier: License :: OSI Approved :: MIT License
Classifier: Programming Language :: Python :: 3
Classifier: Programming Language :: Python :: 3.11
Classifier: Programming Language :: Python :: 3.12
Requires-Dist: pydantic (>=2.9.2,<3.0.0)
Requires-Dist: rich (>=13.9.3,<14.0.0)
Project-URL: Repository, https://github.com/dangrie158/slurmbatcher
